{
	"$schema": "http://schema.management.azure.com/schemas/2015-01-01/deploymentTemplate.json#",
	"contentVersion": "1.0.0.0",
	"parameters": {
		"factoryName": {
			"type": "string",
			"metadata": "Data Factory name",
			"defaultValue": "dfpsmsiidt001"
		}
	},
	"variables": {
		"factoryId": "[concat('Microsoft.DataFactory/factories/', parameters('factoryName'))]"
	},
	"resources": [
		{
			"name": "[concat(parameters('factoryName'), '/PL_MAIN')]",
			"type": "Microsoft.DataFactory/factories/pipelines",
			"apiVersion": "2018-06-01",
			"properties": {
				"activities": [
					{
						"name": "PL_DWH_TABLES",
						"type": "ExecutePipeline",
						"dependsOn": [
							{
								"activity": "PL_COPY_UI_TABLE_insert",
								"dependencyConditions": [
									"Succeeded"
								]
							}
						],
						"userProperties": [],
						"typeProperties": {
							"pipeline": {
								"referenceName": "PL_DWH_TABLES",
								"type": "PipelineReference"
							},
							"waitOnCompletion": true
						}
					},
					{
						"name": "PL_DAILY_MAIN",
						"type": "ExecutePipeline",
						"dependsOn": [
							{
								"activity": "PL_DWH_TABLES",
								"dependencyConditions": [
									"Succeeded"
								]
							}
						],
						"userProperties": [],
						"typeProperties": {
							"pipeline": {
								"referenceName": "PL_DAILY_MAIN",
								"type": "PipelineReference"
							},
							"waitOnCompletion": true
						}
					},
					{
						"name": "PL_CUSTOM_MAIN",
						"type": "ExecutePipeline",
						"dependsOn": [
							{
								"activity": "PL_DWH_TABLES",
								"dependencyConditions": [
									"Succeeded"
								]
							}
						],
						"userProperties": [],
						"typeProperties": {
							"pipeline": {
								"referenceName": "PL_CUSTOM_MAIN",
								"type": "PipelineReference"
							},
							"waitOnCompletion": true
						}
					},
					{
						"name": "DWA_CONTRACT",
						"type": "SqlServerStoredProcedure",
						"dependsOn": [
							{
								"activity": "PL_STOCK_CALCULATE",
								"dependencyConditions": [
									"Succeeded"
								]
							}
						],
						"policy": {
							"timeout": "7.00:00:00",
							"retry": 0,
							"retryIntervalInSeconds": 30,
							"secureOutput": false,
							"secureInput": false
						},
						"userProperties": [],
						"typeProperties": {
							"storedProcedureName": "[[dwh].[P_UPSERT_CONTRACT]"
						},
						"linkedServiceName": {
							"referenceName": "ls_dsqlpqtr",
							"type": "LinkedServiceReference"
						}
					},
					{
						"name": "PL_STOCK_CALCULATE",
						"type": "ExecutePipeline",
						"dependsOn": [
							{
								"activity": "PL_DAILY_MAIN",
								"dependencyConditions": [
									"Succeeded"
								]
							},
							{
								"activity": "PL_CUSTOM_MAIN",
								"dependencyConditions": [
									"Succeeded"
								]
							}
						],
						"userProperties": [],
						"typeProperties": {
							"pipeline": {
								"referenceName": "PL_STOCK_CALCULATE",
								"type": "PipelineReference"
							},
							"waitOnCompletion": true
						}
					},
					{
						"name": "PL_COPY_UI_TABLE_insert",
						"type": "ExecutePipeline",
						"dependsOn": [],
						"userProperties": [],
						"typeProperties": {
							"pipeline": {
								"referenceName": "PL_COPY_UI_TABLE_insert",
								"type": "PipelineReference"
							},
							"waitOnCompletion": true
						}
					}
				],
				"folder": {
					"name": "PL_MAIN"
				},
				"annotations": []
			},
			"dependsOn": []
		}
	]
}